usda_fas/__init__.py
usda_fas/client.py
usda_fas/easy_client.py
usda_fas/api/__init__.py
usda_fas/api/esr.py
usda_fas/api/gats.py
usda_fas/api/psd.py
usda_fas_sdk-0.1.11.dist-info/licenses/LICENSE
usda_fas_sdk-0.1.11.dist-info/METADATA
usda_fas_sdk-0.1.11.dist-info/WHEEL
usda_fas_sdk-0.1.11.dist-info/top_level.txt
usda_fas_sdk-0.1.11.dist-info/RECORD
